Xaunsion/Xaunsion.py
Xaunsion/__init__.py
Xaunsion-0.0.1.dist-info/METADATA
Xaunsion-0.0.1.dist-info/WHEEL
Xaunsion-0.0.1.dist-info/top_level.txt
Xaunsion-0.0.1.dist-info/RECORD
