Metadata-Version: 2.1
Name: Xaunsion
Version: 0.0.1
Summary: This name is reserve for Xaunsion.com for future
Author: Xaunsion
Author-email: <contact@xaunsion.com>
Keywords: python,Xaunsion
Classifier: Operating System :: Unix
Classifier: Operating System :: MacOS :: MacOS X
Classifier: Operating System :: Microsoft :: Windows
